{
  "$schema": "https://developer.microsoft.com/json-schemas/fabric/item/report/definition/bookmark/2.1.0/schema.json",
  "displayName": "Wilson",
  "name": "06c6d3a07ba982b37ecc",
  "options": {
    "targetVisualNames": [
      "7cbae41095f2eff4d2a9",
      "caff970433c3b952e2d7",
      "abbfee0cfdc17f35eeb0"
    ],
    "suppressDisplay": true
  },
  "explorationState": {
    "version": "1.3",
    "activeSection": "75cf4b17c57105de6273",
    "filters": {
      "byExpr": [
        {
          "name": "194e5374e20d6bb5d2a2",
          "type": "Categorical",
          "filter": {
            "Version": 2,
            "From": [
              {
                "Name": "d",
                "Entity": "Dim_Position",
                "Type": 0
              }
            ],
            "Where": [
              {
                "Condition": {
                  "In": {
                    "Expressions": [
                      {
                        "Column": {
                          "Expression": {
                            "SourceRef": {
                              "Source": "d"
                            }
                          },
                          "Property": "FantasyRelevant"
                        }
                      }
                    ],
                    "Values": [
                      [
                        {
                          "Literal": {
                            "Value": "true"
                          }
                        }
                      ]
                    ]
                  }
                }
              }
            ]
          },
          "expression": {
            "Column": {
              "Expression": {
                "SourceRef": {
                  "Entity": "Dim_Position"
                }
              },
              "Property": "FantasyRelevant"
            }
          },
          "howCreated": 1
        },
        {
          "name": "347ee142ed910961350e",
          "type": "Advanced",
          "filter": {
            "Version": 2,
            "From": [
              {
                "Name": "d",
                "Entity": "Dim_NFLPlayers",
                "Type": 0
              }
            ],
            "Where": [
              {
                "Condition": {
                  "And": {
                    "Left": {
                      "Not": {
                        "Expression": {
                          "Comparison": {
                            "ComparisonKind": 0,
                            "Left": {
                              "Column": {
                                "Expression": {
                                  "SourceRef": {
                                    "Source": "d"
                                  }
                                },
                                "Property": "DisplayName"
                              }
                            },
                            "Right": {
                              "Literal": {
                                "Value": "null"
                              }
                            }
                          }
                        }
                      }
                    },
                    "Right": {
                      "Not": {
                        "Expression": {
                          "Comparison": {
                            "ComparisonKind": 0,
                            "Left": {
                              "Column": {
                                "Expression": {
                                  "SourceRef": {
                                    "Source": "d"
                                  }
                                },
                                "Property": "DisplayName"
                              }
                            },
                            "Right": {
                              "Literal": {
                                "Value": "''"
                              }
                            }
                          }
                        }
                      }
                    }
                  }
                }
              }
            ]
          },
          "expression": {
            "Column": {
              "Expression": {
                "SourceRef": {
                  "Entity": "Dim_NFLPlayers"
                }
              },
              "Property": "DisplayName"
            }
          },
          "howCreated": 1
        }
      ]
    },
    "sections": {
      "75cf4b17c57105de6273": {
        "visualContainers": {
          "abbfee0cfdc17f35eeb0": {
            "filters": {
              "byExpr": [
                {
                  "name": "699874e2f4505a06eb9c",
                  "type": "Categorical",
                  "expression": {
                    "Column": {
                      "Expression": {
                        "SourceRef": {
                          "Entity": "Dim_FantasyTeams"
                        }
                      },
                      "Property": "Division"
                    }
                  },
                  "howCreated": 0
                }
              ]
            },
            "singleVisual": {
              "visualType": "slicer",
              "objects": {
                "merge": {
                  "general": [
                    {
                      "properties": {
                        "filter": {
                          "filter": {
                            "Version": 2,
                            "From": [
                              {
                                "Name": "d",
                                "Entity": "Dim_FantasyTeams",
                                "Type": 0
                              }
                            ],
                            "Where": [
                              {
                                "Condition": {
                                  "In": {
                                    "Expressions": [
                                      {
                                        "Column": {
                                          "Expression": {
                                            "SourceRef": {
                                              "Source": "d"
                                            }
                                          },
                                          "Property": "Division"
                                        }
                                      }
                                    ],
                                    "Values": [
                                      [
                                        {
                                          "Literal": {
                                            "Value": "'Wilson'"
                                          }
                                        }
                                      ]
                                    ]
                                  }
                                }
                              }
                            ]
                          }
                        }
                      }
                    }
                  ],
                  "data": [
                    {
                      "properties": {
                        "mode": {
                          "expr": {
                            "Literal": {
                              "Value": "'Basic'"
                            }
                          }
                        }
                      }
                    }
                  ]
                }
              },
              "activeProjections": {
                "Values": [
                  {
                    "Column": {
                      "Expression": {
                        "SourceRef": {
                          "Entity": "Dim_FantasyTeams"
                        }
                      },
                      "Property": "Division"
                    }
                  }
                ]
              },
              "display": {
                "mode": "hidden"
              }
            }
          },
          "36957bb1243c79746297": {
            "filters": {
              "byExpr": [
                {
                  "name": "8110bb91a2bf1bf7ad45",
                  "type": "Advanced",
                  "expression": {
                    "Column": {
                      "Expression": {
                        "SourceRef": {
                          "Entity": "Fact_FantasyTeams"
                        }
                      },
                      "Property": "ContractValue"
                    }
                  },
                  "howCreated": 0
                }
              ]
            },
            "singleVisual": {
              "visualType": "slicer",
              "objects": {
                "merge": {
                  "data": [
                    {
                      "properties": {
                        "numericEnd": {
                          "expr": {
                            "Literal": {
                              "Value": "27D"
                            }
                          }
                        },
                        "mode": {
                          "expr": {
                            "Literal": {
                              "Value": "'Between'"
                            }
                          }
                        }
                      }
                    }
                  ]
                }
              },
              "activeProjections": {
                "Values": [
                  {
                    "Column": {
                      "Expression": {
                        "SourceRef": {
                          "Entity": "Fact_FantasyTeams"
                        }
                      },
                      "Property": "ContractValue"
                    }
                  }
                ]
              }
            }
          },
          "6949b0a00715222a8b32": {
            "filters": {
              "byExpr": [
                {
                  "name": "c4425ab6e170e70918ce",
                  "type": "Categorical",
                  "filter": {
                    "Version": 2,
                    "From": [
                      {
                        "Name": "d",
                        "Entity": "Dim_Division",
                        "Type": 0
                      }
                    ],
                    "Where": [
                      {
                        "Condition": {
                          "Not": {
                            "Expression": {
                              "In": {
                                "Expressions": [
                                  {
                                    "Column": {
                                      "Expression": {
                                        "SourceRef": {
                                          "Source": "d"
                                        }
                                      },
                                      "Property": "division_name"
                                    }
                                  }
                                ],
                                "Values": [
                                  [
                                    {
                                      "Literal": {
                                        "Value": "null"
                                      }
                                    }
                                  ]
                                ]
                              }
                            }
                          }
                        }
                      }
                    ]
                  },
                  "expression": {
                    "Column": {
                      "Expression": {
                        "SourceRef": {
                          "Entity": "Dim_Division"
                        }
                      },
                      "Property": "division_name"
                    }
                  },
                  "howCreated": 1
                },
                {
                  "name": "eb87111d22918c7fe527",
                  "type": "Categorical",
                  "expression": {
                    "Column": {
                      "Expression": {
                        "SourceRef": {
                          "Entity": "Dim_NFLPlayers"
                        }
                      },
                      "Property": "DisplayName"
                    }
                  },
                  "howCreated": 0
                },
                {
                  "name": "ce538651cde181c9ff04",
                  "type": "Categorical",
                  "expression": {
                    "Column": {
                      "Expression": {
                        "SourceRef": {
                          "Entity": "Dim_Position"
                        }
                      },
                      "Property": "PositionGroup"
                    }
                  },
                  "howCreated": 0
                },
                {
                  "name": "4088462bd0e5ae589835",
                  "type": "Categorical",
                  "expression": {
                    "Column": {
                      "Expression": {
                        "SourceRef": {
                          "Entity": "Dim_Contract"
                        }
                      },
                      "Property": "ContractID"
                    }
                  },
                  "howCreated": 0
                },
                {
                  "name": "968f1472cce3bc552ccd",
                  "type": "Advanced",
                  "expression": {
                    "Column": {
                      "Expression": {
                        "SourceRef": {
                          "Entity": "Dim_NFLPlayers"
                        }
                      },
                      "Property": "Age"
                    }
                  },
                  "howCreated": 0
                },
                {
                  "name": "786f1ba1deca9d03a4b8",
                  "type": "Advanced",
                  "expression": {
                    "Measure": {
                      "Expression": {
                        "SourceRef": {
                          "Entity": "_Measures"
                        }
                      },
                      "Property": "Contract Value"
                    }
                  },
                  "howCreated": 0
                },
                {
                  "name": "55da689c870b24291f67",
                  "type": "Advanced",
                  "expression": {
                    "Measure": {
                      "Expression": {
                        "SourceRef": {
                          "Entity": "_Measures"
                        }
                      },
                      "Property": "Dead Money - Speculative - Current Year"
                    }
                  },
                  "howCreated": 0
                },
                {
                  "name": "1e64bb49ab9c2fde470f",
                  "type": "Advanced",
                  "expression": {
                    "Measure": {
                      "Expression": {
                        "SourceRef": {
                          "Entity": "_Measures"
                        }
                      },
                      "Property": "Dead Money - Speculative - Total"
                    }
                  },
                  "howCreated": 0
                },
                {
                  "name": "d931e37759b4b5270576",
                  "type": "Advanced",
                  "expression": {
                    "Measure": {
                      "Expression": {
                        "SourceRef": {
                          "Entity": "_Measures"
                        }
                      },
                      "Property": "ADP"
                    }
                  },
                  "howCreated": 0
                }
              ]
            },
            "singleVisual": {
              "visualType": "tableEx",
              "objects": {},
              "orderBy": [
                {
                  "Direction": 2,
                  "Expression": {
                    "Measure": {
                      "Expression": {
                        "SourceRef": {
                          "Entity": "_Measures"
                        }
                      },
                      "Property": "Contract Value"
                    }
                  }
                }
              ]
            }
          },
          "89db1379b22fc8f25575": {
            "filters": {
              "byExpr": [
                {
                  "name": "55acf68b7f7468fafa86",
                  "type": "Categorical",
                  "filter": {
                    "Version": 2,
                    "From": [
                      {
                        "Name": "d",
                        "Entity": "Dim_NFLTeams",
                        "Type": 0
                      }
                    ],
                    "Where": [
                      {
                        "Condition": {
                          "Not": {
                            "Expression": {
                              "In": {
                                "Expressions": [
                                  {
                                    "Column": {
                                      "Expression": {
                                        "SourceRef": {
                                          "Source": "d"
                                        }
                                      },
                                      "Property": "TeamName"
                                    }
                                  }
                                ],
                                "Values": [
                                  [
                                    {
                                      "Literal": {
                                        "Value": "null"
                                      }
                                    }
                                  ]
                                ]
                              }
                            }
                          }
                        }
                      }
                    ]
                  },
                  "expression": {
                    "Column": {
                      "Expression": {
                        "SourceRef": {
                          "Entity": "Dim_NFLTeams"
                        }
                      },
                      "Property": "TeamName"
                    }
                  },
                  "howCreated": 0
                },
                {
                  "name": "77c150f5b28394d1a356",
                  "type": "Categorical",
                  "expression": {
                    "Column": {
                      "Expression": {
                        "SourceRef": {
                          "Entity": "Dim_NFLTeams"
                        }
                      },
                      "Property": "TeamConf"
                    }
                  },
                  "howCreated": 0
                }
              ]
            },
            "singleVisual": {
              "visualType": "slicer",
              "objects": {
                "merge": {
                  "data": [
                    {
                      "properties": {
                        "mode": {
                          "expr": {
                            "Literal": {
                              "Value": "'Dropdown'"
                            }
                          }
                        }
                      }
                    }
                  ]
                }
              },
              "activeProjections": {
                "Values": [
                  {
                    "Column": {
                      "Expression": {
                        "SourceRef": {
                          "Entity": "Dim_NFLTeams"
                        }
                      },
                      "Property": "TeamConf"
                    }
                  }
                ]
              }
            }
          },
          "45c3c5fabfb14d157bfa": {
            "filters": {
              "byExpr": [
                {
                  "name": "24905c9713fa761f319b",
                  "type": "Advanced",
                  "expression": {
                    "Column": {
                      "Expression": {
                        "SourceRef": {
                          "Entity": "Dim_NFLPlayers"
                        }
                      },
                      "Property": "Age"
                    }
                  },
                  "howCreated": 0
                }
              ]
            },
            "singleVisual": {
              "visualType": "slicer",
              "objects": {
                "merge": {
                  "data": [
                    {
                      "properties": {
                        "mode": {
                          "expr": {
                            "Literal": {
                              "Value": "'Between'"
                            }
                          }
                        }
                      }
                    }
                  ]
                }
              },
              "activeProjections": {
                "Values": [
                  {
                    "Column": {
                      "Expression": {
                        "SourceRef": {
                          "Entity": "Dim_NFLPlayers"
                        }
                      },
                      "Property": "Age"
                    }
                  }
                ]
              }
            }
          },
          "7232377d7a2cdb99a5df": {
            "filters": {
              "byExpr": [
                {
                  "name": "a1e9bc70db0117199ba1",
                  "type": "Categorical",
                  "expression": {
                    "Column": {
                      "Expression": {
                        "SourceRef": {
                          "Entity": "Dim_Position"
                        }
                      },
                      "Property": "SideOfBall"
                    }
                  },
                  "howCreated": 0
                },
                {
                  "name": "c8db122ed559b4b1efc5",
                  "type": "Categorical",
                  "expression": {
                    "Column": {
                      "Expression": {
                        "SourceRef": {
                          "Entity": "Dim_Position"
                        }
                      },
                      "Property": "PositionGroup"
                    }
                  },
                  "howCreated": 0
                }
              ]
            },
            "singleVisual": {
              "visualType": "slicer",
              "objects": {
                "merge": {
                  "general": [
                    {
                      "properties": {
                        "filter": {
                          "filter": {
                            "Version": 2,
                            "From": [
                              {
                                "Name": "d",
                                "Entity": "Dim_Position",
                                "Type": 0
                              }
                            ],
                            "Where": [
                              {
                                "Condition": {
                                  "In": {
                                    "Expressions": [
                                      {
                                        "Column": {
                                          "Expression": {
                                            "SourceRef": {
                                              "Source": "d"
                                            }
                                          },
                                          "Property": "SideOfBall"
                                        }
                                      }
                                    ],
                                    "Values": [
                                      [
                                        {
                                          "Literal": {
                                            "Value": "'Offense'"
                                          }
                                        }
                                      ]
                                    ]
                                  }
                                }
                              }
                            ]
                          }
                        }
                      }
                    }
                  ],
                  "data": [
                    {
                      "properties": {
                        "mode": {
                          "expr": {
                            "Literal": {
                              "Value": "'Dropdown'"
                            }
                          }
                        }
                      }
                    }
                  ]
                }
              },
              "activeProjections": {
                "Values": [
                  {
                    "Column": {
                      "Expression": {
                        "SourceRef": {
                          "Entity": "Dim_Position"
                        }
                      },
                      "Property": "SideOfBall"
                    }
                  }
                ]
              },
              "cachedFilterDisplayItems": [
                {
                  "id": {
                    "scopeId": {
                      "Comparison": {
                        "ComparisonKind": 0,
                        "Left": {
                          "Column": {
                            "Expression": {
                              "SourceRef": {
                                "Entity": "Dim_Position"
                              }
                            },
                            "Property": "SideOfBall"
                          }
                        },
                        "Right": {
                          "Literal": {
                            "Value": "'Offense'"
                          }
                        }
                      }
                    }
                  },
                  "displayName": "Offense"
                }
              ],
              "expansionStates": [
                {
                  "roles": [
                    "Values"
                  ],
                  "levels": [
                    {
                      "queryRefs": [
                        "Dim_Position.SideOfBall"
                      ],
                      "isCollapsed": true,
                      "identityKeys": [
                        {
                          "Column": {
                            "Expression": {
                              "SourceRef": {
                                "Entity": "Dim_Position"
                              }
                            },
                            "Property": "SideOfBall"
                          }
                        }
                      ],
                      "isPinned": true
                    },
                    {
                      "queryRefs": [
                        "Dim_Position.PositionGroup"
                      ],
                      "isCollapsed": true,
                      "isPinned": true
                    }
                  ],
                  "root": {
                    "identityValues": []
                  }
                }
              ]
            }
          },
          "f0b578108aef023038eb": {
            "filters": {
              "byExpr": [
                {
                  "name": "55acf68b7f7468fafa86",
                  "type": "Categorical",
                  "filter": {
                    "Version": 2,
                    "From": [
                      {
                        "Name": "d",
                        "Entity": "Dim_NFLTeams",
                        "Type": 0
                      }
                    ],
                    "Where": [
                      {
                        "Condition": {
                          "Not": {
                            "Expression": {
                              "In": {
                                "Expressions": [
                                  {
                                    "Column": {
                                      "Expression": {
                                        "SourceRef": {
                                          "Source": "d"
                                        }
                                      },
                                      "Property": "TeamName"
                                    }
                                  }
                                ],
                                "Values": [
                                  [
                                    {
                                      "Literal": {
                                        "Value": "null"
                                      }
                                    }
                                  ]
                                ]
                              }
                            }
                          }
                        }
                      }
                    ]
                  },
                  "expression": {
                    "Column": {
                      "Expression": {
                        "SourceRef": {
                          "Entity": "Dim_NFLTeams"
                        }
                      },
                      "Property": "TeamName"
                    }
                  },
                  "howCreated": 1
                },
                {
                  "name": "a228e3434e22e7d05b37",
                  "type": "Categorical",
                  "expression": {
                    "Column": {
                      "Expression": {
                        "SourceRef": {
                          "Entity": "Dim_NFLPlayers"
                        }
                      },
                      "Property": "DisplayName"
                    }
                  },
                  "howCreated": 0
                }
              ]
            },
            "singleVisual": {
              "visualType": "slicer",
              "objects": {
                "merge": {
                  "data": [
                    {
                      "properties": {
                        "mode": {
                          "expr": {
                            "Literal": {
                              "Value": "'Dropdown'"
                            }
                          }
                        }
                      }
                    }
                  ]
                }
              },
              "activeProjections": {
                "Values": [
                  {
                    "Column": {
                      "Expression": {
                        "SourceRef": {
                          "Entity": "Dim_NFLPlayers"
                        }
                      },
                      "Property": "DisplayName"
                    }
                  }
                ]
              }
            }
          },
          "a5c588735148958a1050": {
            "filters": {
              "byExpr": [
                {
                  "name": "c4425ab6e170e70918ce",
                  "type": "Categorical",
                  "filter": {
                    "Version": 2,
                    "From": [
                      {
                        "Name": "d",
                        "Entity": "Dim_Division",
                        "Type": 0
                      }
                    ],
                    "Where": [
                      {
                        "Condition": {
                          "Not": {
                            "Expression": {
                              "In": {
                                "Expressions": [
                                  {
                                    "Column": {
                                      "Expression": {
                                        "SourceRef": {
                                          "Source": "d"
                                        }
                                      },
                                      "Property": "division_name"
                                    }
                                  }
                                ],
                                "Values": [
                                  [
                                    {
                                      "Literal": {
                                        "Value": "null"
                                      }
                                    }
                                  ]
                                ]
                              }
                            }
                          }
                        }
                      }
                    ]
                  },
                  "expression": {
                    "Column": {
                      "Expression": {
                        "SourceRef": {
                          "Entity": "Dim_Division"
                        }
                      },
                      "Property": "division_name"
                    }
                  },
                  "howCreated": 1
                },
                {
                  "name": "f67cdd40e90f21595356",
                  "type": "Categorical",
                  "expression": {
                    "Column": {
                      "Expression": {
                        "SourceRef": {
                          "Entity": "Dim_NFLPlayers"
                        }
                      },
                      "Property": "DisplayName"
                    }
                  },
                  "howCreated": 0
                },
                {
                  "name": "22cdab3ece8b0c00e10a",
                  "type": "Categorical",
                  "expression": {
                    "Column": {
                      "Expression": {
                        "SourceRef": {
                          "Entity": "Dim_Position"
                        }
                      },
                      "Property": "PositionGroup"
                    }
                  },
                  "howCreated": 0
                },
                {
                  "name": "7f8bbeadc3ecefc5ce74",
                  "type": "Categorical",
                  "expression": {
                    "Column": {
                      "Expression": {
                        "SourceRef": {
                          "Entity": "Dim_Contract"
                        }
                      },
                      "Property": "ContractID"
                    }
                  },
                  "howCreated": 0
                },
                {
                  "name": "e71e2a38707259d783a2",
                  "type": "Advanced",
                  "expression": {
                    "Column": {
                      "Expression": {
                        "SourceRef": {
                          "Entity": "Dim_NFLPlayers"
                        }
                      },
                      "Property": "Age"
                    }
                  },
                  "howCreated": 0
                },
                {
                  "name": "d81af4dc59cde733b2bc",
                  "type": "Advanced",
                  "expression": {
                    "Measure": {
                      "Expression": {
                        "SourceRef": {
                          "Entity": "_Measures"
                        }
                      },
                      "Property": "Contract Value"
                    }
                  },
                  "howCreated": 0
                },
                {
                  "name": "14c5f53d7cc4ce23d204",
                  "type": "Advanced",
                  "expression": {
                    "Measure": {
                      "Expression": {
                        "SourceRef": {
                          "Entity": "_Measures"
                        }
                      },
                      "Property": "Dead Money - Speculative - Current Year"
                    }
                  },
                  "howCreated": 0
                },
                {
                  "name": "1c0d595c99fcb9e6b37c",
                  "type": "Advanced",
                  "expression": {
                    "Measure": {
                      "Expression": {
                        "SourceRef": {
                          "Entity": "_Measures"
                        }
                      },
                      "Property": "Dead Money - Speculative - Total"
                    }
                  },
                  "howCreated": 0
                },
                {
                  "name": "6ab57714ae8970c9d822",
                  "type": "Advanced",
                  "expression": {
                    "Measure": {
                      "Expression": {
                        "SourceRef": {
                          "Entity": "_Measures"
                        }
                      },
                      "Property": "ADP"
                    }
                  },
                  "howCreated": 0
                }
              ]
            },
            "singleVisual": {
              "visualType": "tableEx",
              "objects": {},
              "orderBy": [
                {
                  "Direction": 2,
                  "Expression": {
                    "Measure": {
                      "Expression": {
                        "SourceRef": {
                          "Entity": "_Measures"
                        }
                      },
                      "Property": "Contract Value"
                    }
                  }
                }
              ]
            }
          },
          "7cbae41095f2eff4d2a9": {
            "filters": {
              "byExpr": [
                {
                  "name": "461d209dcac4e59dd6bb",
                  "type": "Categorical",
                  "expression": {
                    "Column": {
                      "Expression": {
                        "SourceRef": {
                          "Entity": "Dim_FantasyTeams"
                        }
                      },
                      "Property": "TeamName"
                    }
                  },
                  "howCreated": 0
                }
              ]
            },
            "singleVisual": {
              "visualType": "slicer",
              "objects": {
                "merge": {
                  "data": [
                    {
                      "properties": {
                        "mode": {
                          "expr": {
                            "Literal": {
                              "Value": "'Dropdown'"
                            }
                          }
                        }
                      }
                    }
                  ]
                }
              },
              "activeProjections": {
                "Values": [
                  {
                    "Column": {
                      "Expression": {
                        "SourceRef": {
                          "Entity": "Dim_FantasyTeams"
                        }
                      },
                      "Property": "TeamName"
                    }
                  }
                ]
              }
            }
          },
          "caff970433c3b952e2d7": {
            "filters": {
              "byExpr": [
                {
                  "name": "884123f8e00ed90a076c",
                  "type": "Categorical",
                  "expression": {
                    "Column": {
                      "Expression": {
                        "SourceRef": {
                          "Entity": "Dim_FantasyTeams"
                        }
                      },
                      "Property": "TeamName"
                    }
                  },
                  "howCreated": 0
                }
              ]
            },
            "singleVisual": {
              "visualType": "slicer",
              "objects": {
                "merge": {
                  "data": [
                    {
                      "properties": {
                        "mode": {
                          "expr": {
                            "Literal": {
                              "Value": "'Dropdown'"
                            }
                          }
                        }
                      }
                    }
                  ]
                }
              },
              "activeProjections": {
                "Values": [
                  {
                    "Column": {
                      "Expression": {
                        "SourceRef": {
                          "Entity": "Dim_FantasyTeams"
                        }
                      },
                      "Property": "TeamName"
                    }
                  }
                ]
              }
            }
          }
        }
      }
    },
    "objects": {
      "merge": {
        "outspacePane": [
          {
            "properties": {
              "expanded": {
                "expr": {
                  "Literal": {
                    "Value": "false"
                  }
                }
              }
            }
          }
        ]
      }
    }
  }
}